{
    "CompleterNpc": "Гром",
    "NextQuestId": 2,
    "RandomReward": 0b,
    "QuestRepeat": 0,
    "QuestCompletion": 0,
    "IgnoreNBT": 0b,
    "Title": "Отдать грому красную пыль.",
    "Text": "Отдать грому красную пыль в сундуке.",
    "QuestFactionPoints": {
        "DecreaseFaction1Points": 0b,
        "OptionFaction2Points": 100,
        "OptionFactions1": -1,
        "OptionFactions2": -1,
        "OptionFaction1Points": 100,
        "DecreaseFaction2Points": 0b
    },
    "RewardExp": 0,
    "QuestCommand": "",
    "ModRev": 17,
    "Type": 0,
    "QuestMail": {
        "Sender": "",
        "BeenRead": 0b,
        "Message": {
        },
        "MailItems": [
        ],
        "MailQuest": -1,
        "TimePast": 1560094669276L,
        "Time": 0L,
        "Subject": ""
    },
    "IgnoreDamage": 0b,
    "Rewards": {
        "NpcMiscInv": [
            {
                "Slot": 0b,
                "id": "customnpcs:npcStoneGun",
                "Count": 1b,
                "Damage": 0s
            },
            {
                "Slot": 1b,
                "id": "customnpcs:npcStoneDagger",
                "Count": 1b,
                "Damage": 0s
            },
            {
                "Slot": 2b,
                "id": "customnpcs:npcStoneBullet",
                "Count": 20b,
                "Damage": 0s
            }
        ]
    },
    "Items": {
        "NpcMiscInv": [
            {
                "Slot": 0b,
                "id": "minecraft:redstone",
                "Count": 1b,
                "Damage": 0s
            }
        ]
    },
    "LeaveItems": 0b,
    "CompleteText": "Так, сейчас попробую. А вот вроде открылась. Так слушай, тут мы с тем парнем долго готовились сбежать, так что вот держи ружье и кинжал. По туннелю придешь ко мне, откроешь дверь мне, а я попробую главные открыть.",
    "NextQuestTitle": "Выбраться"
}
